anndata2ri/__init__.py
anndata2ri/_conv.py
anndata2ri/_conv_name.py
anndata2ri/_ipython.py
anndata2ri/_py2r.py
anndata2ri/_r2py.py
anndata2ri/_rpy2_ext.py
anndata2ri/_version.py
anndata2ri/py.typed
anndata2ri/test_utils.py
anndata2ri/scipy2ri/__init__.py
anndata2ri/scipy2ri/_conv.py
anndata2ri/scipy2ri/_py2r.py
anndata2ri/scipy2ri/_py2r_helpers.r
anndata2ri/scipy2ri/_r2py.py
anndata2ri/scipy2ri/_support.py
anndata2ri-2.0.dist-info/METADATA
anndata2ri-2.0.dist-info/WHEEL
anndata2ri-2.0.dist-info/licenses/LICENSE
anndata2ri-2.0.dist-info/RECORD
