Metadata-Version: 2.4
Name: anndata2ri
Version: 2.0
Project-URL: Documentation, https://icb-anndata2ri.readthedocs-hosted.com/
Project-URL: Issue Tracker, https://github.com/theislab/anndata2ri/issues?q=is%3Aissue+is%3Aopen+sort%3Aupdated-desc
Project-URL: Source Code, https://github.com/theislab/anndata2ri
Author-email: "Philipp A." <flying-sheep@web.de>
License-File: LICENSE
Classifier: Development Status :: 4 - Beta
Classifier: Intended Audience :: Developers
Classifier: Intended Audience :: Science/Research
Classifier: License :: OSI Approved :: GNU General Public License v3 or later (GPLv3+)
Classifier: Programming Language :: Python :: 3 :: Only
Classifier: Programming Language :: Python :: 3.11
Classifier: Programming Language :: Python :: 3.12
Classifier: Programming Language :: Python :: 3.13
Classifier: Programming Language :: R
Classifier: Topic :: Scientific/Engineering :: Bio-Informatics
Requires-Python: >=3.11
Requires-Dist: anndata
Requires-Dist: rpy2>=3.5.2
Requires-Dist: tzlocal
Provides-Extra: dev
Requires-Dist: pre-commit; extra == 'dev'
Requires-Dist: scipy-stubs; extra == 'dev'
Provides-Extra: doc
Requires-Dist: ipython; extra == 'doc'
Requires-Dist: lxml; extra == 'doc'
Requires-Dist: scanpydoc[theme,typehints]; extra == 'doc'
Requires-Dist: sphinx; extra == 'doc'
Provides-Extra: test
Requires-Dist: pygments; extra == 'test'
Requires-Dist: pytest; extra == 'test'
Requires-Dist: pytest-faulthandler; extra == 'test'
Requires-Dist: scanpy; extra == 'test'
